pydlj/__init__.py
pydlj/base.py
pydlj/exceptions.py
pydlj/shorteners/__init__.py
pydlj/shorteners/adfly.py
pydlj/shorteners/bitly.py
pydlj/shorteners/cf.py
pydlj/shorteners/chilpit.py
pydlj/shorteners/clckru.py
pydlj/shorteners/cuttly.py
pydlj/shorteners/dagd.py
pydlj/shorteners/flydev.py
pydlj/shorteners/gitio.py
pydlj/shorteners/iplc.py
pydlj/shorteners/isgd.py
pydlj/shorteners/nullpointer.py
pydlj/shorteners/osdb.py
pydlj/shorteners/owly.py
pydlj/shorteners/post.py
pydlj/shorteners/qpsru.py
pydlj/shorteners/shortcm.py
pydlj/shorteners/tinycc.py
pydlj/shorteners/tinyurl.py
pydlj-0.0.3.dist-info/WHEEL
pydlj-0.0.3.dist-info/METADATA
pydlj-0.0.3.dist-info/RECORD
