Metadata-Version: 2.1
Name: pydlj
Version: 0.0.3
Summary: A url shortner
Author: Tomy
Author-email: cyaeyz@gmail.com
Requires-Python: >=3.8,<4.0
Classifier: Programming Language :: Python :: 3
Classifier: Programming Language :: Python :: 3.10
Classifier: Programming Language :: Python :: 3.8
Classifier: Programming Language :: Python :: 3.9
